chorusapi/__init__.py
chorusapi/client.py
chorusapi/constants/__init__.py
chorusapi/constants/api_constant.py
chorusapi/constants/etat_courant_flux.py
chorusapi/constants/syntax_flux_constant.py
chorusapi/exceptions/__init__.py
chorusapi/exceptions/exception.py
chorusapi/models/__init__.py
chorusapi/models/api.py
chorusapi/models/factures.py
chorusapi/models/structures.py
chorusapi/models/transverses.py
chorusapi/responses/__init__.py
chorusapi/responses/api_response.py
chorusapi/utils/__init__.py
chorusapi/utils/chorus_utils.py
exemples/__init__.py
exemples/deposer_facture.py
exemples/env.py
exemples/get_token.py
exemples/recherche_structure.py
exemples/status_depot.py
exemples/utils/etat_courant_flux.py
exemples/utils/print_dict.py
chorus_api-1.0.5.dist-info/LICENSE
chorus_api-1.0.5.dist-info/METADATA
chorus_api-1.0.5.dist-info/WHEEL
chorus_api-1.0.5.dist-info/top_level.txt
chorus_api-1.0.5.dist-info/RECORD
