Metadata-Version: 2.1
Name: chorus-api
Version: 1.0.5
Summary: Chorus API Package https://piste.gouv.fr
Home-page: https://github.com/cnfilms/chorus-api
Author: Joel ONIPOH
Author-email: technique@cinego.net
Project-URL: Bug Tracker, https://github.com/cnfilms/chorus-api/issues
Project-URL: Changelog, https://github.com/cnfilms/chorus-api/releases
Keywords: python,chorus,api,piste,chorus piste
Classifier: Programming Language :: Python :: 2
Classifier: Programming Language :: Python :: 3
Classifier: License :: OSI Approved :: MIT License
Classifier: Operating System :: OS Independent
Requires-Python: >=2.7
License-File: LICENSE
Requires-Dist: requests
